MANIFEST.in
README.txt
setup.cfg
setup.py
uvsq.theme-configure.zcml
docs/HISTORY.txt
docs/INSTALL.txt
docs/LICENSE.txt
uvsq/__init__.py
uvsq.theme.egg-info/PKG-INFO
uvsq.theme.egg-info/SOURCES.txt
uvsq.theme.egg-info/dependency_links.txt
uvsq.theme.egg-info/entry_points.txt
uvsq.theme.egg-info/namespace_packages.txt
uvsq.theme.egg-info/not-zip-safe
uvsq.theme.egg-info/paster_plugins.txt
uvsq.theme.egg-info/requires.txt
uvsq.theme.egg-info/top_level.txt
uvsq/theme/__init__.py
uvsq/theme/configure.zcml
uvsq/theme/profiles.zcml
uvsq/theme/setuphandlers.py
uvsq/theme/skins.zcml
uvsq/theme/tests.py
uvsq/theme/version.txt
uvsq/theme/browser/__init__.py
uvsq/theme/browser/configure.zcml
uvsq/theme/browser/interfaces.py
uvsq/theme/browser/viewlet.pt
uvsq/theme/browser/viewlets.py
uvsq/theme/browser/image/README.txt
uvsq/theme/browser/image/ajax-loader.gif
uvsq/theme/browser/image/ajax-loader2.gif
uvsq/theme/browser/image/calendar.png
uvsq/theme/browser/image/crumbs.png
uvsq/theme/browser/image/fond_off.png
uvsq/theme/browser/image/fond_off2.png
uvsq/theme/browser/image/logo.jpg
uvsq/theme/browser/image/logo_ecampus2.png
uvsq/theme/browser/image/pb_close.png
uvsq/theme/browser/image/portal-header.png
uvsq/theme/browser/image/tag_mask.png
uvsq/theme/browser/image/time.png
uvsq/theme/browser/image/uvsq-logo.png
uvsq/theme/browser/image/cat/cat_aide.png
uvsq/theme/browser/image/cat/cat_bug.png
uvsq/theme/browser/image/cat/cat_communaute.png
uvsq/theme/browser/image/cat/cat_communaute.psd
uvsq/theme/browser/image/cat/cat_ecampus1.png
uvsq/theme/browser/image/cat/cat_fichiers.png
uvsq/theme/browser/image/cat/cat_glossaire.png
uvsq/theme/browser/image/cat/cat_ressources.png
uvsq/theme/browser/image/cat/cat_sonorisation.png
uvsq/theme/browser/image/cat/cat_webconf.png
uvsq/theme/browser/image/cat/cat_wims.png
uvsq/theme/browser/image/country-flags/cn.gif
uvsq/theme/browser/image/country-flags/fr.gif
uvsq/theme/browser/image/country-flags/gb.gif
uvsq/theme/browser/image/country-flags/it.gif
uvsq/theme/browser/image/fonts/IcoMoon.eot
uvsq/theme/browser/image/fonts/IcoMoon.svg
uvsq/theme/browser/image/fonts/IcoMoon.ttf
uvsq/theme/browser/image/fonts/IcoMoon.woff
uvsq/theme/browser/image/menu/ico-cours.png
uvsq/theme/browser/image/menu/ico-deco.png
uvsq/theme/browser/image/menu/ico-espace.png
